django_sixpack-1.0.4.dist-info/RECORD
django_sixpack-1.0.4.dist-info/zip-safe
django_sixpack-1.0.4.dist-info/DESCRIPTION.rst
django_sixpack-1.0.4.dist-info/top_level.txt
django_sixpack-1.0.4.dist-info/WHEEL
django_sixpack-1.0.4.dist-info/pydist.json
django_sixpack-1.0.4.dist-info/METADATA
djsixpack/__init__.py
djsixpack/djsixpack.py
djsixpack/models.py
djsixpack/tests/__init__.py
djsixpack/tests/class_tests.py
