Metadata-Version: 2.0
Name: django-sixpack
Version: 1.0.4
Summary: A django-friendly wrapper for sixpack-py
Home-page: https://github.com/waveaccounting/django-sixpack
Author: Dan Langer
Author-email: opensource@waveapps.com
License: LICENSE
Platform: UNKNOWN
Classifier: Development Status :: 5 - Production/Stable
Classifier: Framework :: Django
Classifier: Natural Language :: English
Classifier: Programming Language :: Python
Classifier: License :: OSI Approved :: BSD License
Classifier: Operating System :: OS Independent
Requires-Dist: Django (>=1.4)
Requires-Dist: sixpack-client (==1.0.0)
